query_test_pkg/__init__.py
query_test_pkg/query.py
query_test_pkg-0.0.1.dist-info/METADATA
query_test_pkg-0.0.1.dist-info/WHEEL
query_test_pkg-0.0.1.dist-info/top_level.txt
query_test_pkg-0.0.1.dist-info/RECORD
